MANIFEST.in
setup.cfg
setup.py
tw/__init__.py
tw.extjs.egg-info/PKG-INFO
tw.extjs.egg-info/SOURCES.txt
tw.extjs.egg-info/dependency_links.txt
tw.extjs.egg-info/entry_points.txt
tw.extjs.egg-info/namespace_packages.txt
tw.extjs.egg-info/requires.txt
tw.extjs.egg-info/top_level.txt
tw.extjs.egg-info/zip-safe
tw/extjs/__init__.py
tw/extjs/base.py
tw/extjs/extensions.py
tw/extjs/grid.py
tw/extjs/multiselect.py
tw/extjs/panel.py
tw/extjs/release.py
tw/extjs/samples.py
tw/extjs/singleselectcombo.py
tw/extjs/tabs.py
tw/extjs/treeview.py
tw/extjs/static/DDView.js
tw/extjs/static/Multiselect.js
tw/extjs/static/ext-all.js
tw/extjs/static/ext-core.js
tw/extjs/static/ext-jquery-adapter.js
tw/extjs/static/ext-prototype-adapter.js
tw/extjs/static/ext-yui-adapter.js
tw/extjs/static/jquery-plugins.js
tw/extjs/static/s.gif
tw/extjs/static/adapter/ext/ext-base.js
tw/extjs/static/adapter/jquery/ext-jquery-adapter.js
tw/extjs/static/adapter/jquery/jquery.js
tw/extjs/static/adapter/prototype/effects.js
tw/extjs/static/adapter/prototype/ext-prototype-adapter.js
tw/extjs/static/adapter/prototype/prototype.js
tw/extjs/static/adapter/prototype/scriptaculous.js
tw/extjs/static/adapter/yui/ext-yui-adapter.js
tw/extjs/static/adapter/yui/yui-utilities.js
tw/extjs/static/locale/ext-lang-da.js
tw/extjs/static/locale/ext-lang-de.js
tw/extjs/static/locale/ext-lang-en.js
tw/extjs/static/locale/ext-lang-es.js
tw/extjs/static/locale/ext-lang-fr_CA.js
tw/extjs/static/locale/ext-lang-hr.js
tw/extjs/static/locale/ext-lang-hu.js
tw/extjs/static/locale/ext-lang-it.js
tw/extjs/static/locale/ext-lang-ja.js
tw/extjs/static/locale/ext-lang-lv.js
tw/extjs/static/locale/ext-lang-mk.js
tw/extjs/static/locale/ext-lang-nl.js
tw/extjs/static/locale/ext-lang-no.js
tw/extjs/static/locale/ext-lang-pl.js
tw/extjs/static/locale/ext-lang-pt_br.js
tw/extjs/static/locale/ext-lang-ro.js
tw/extjs/static/locale/ext-lang-ru.js
tw/extjs/static/locale/ext-lang-sk.js
tw/extjs/static/locale/ext-lang-sv_se.js
tw/extjs/static/locale/ext-lang-tr.js
tw/extjs/static/locale/ext-lang-vn.js
tw/extjs/static/locale/ext-lang-zh_CN.js
tw/extjs/static/locale/ext-lang-zh_TW.js
tw/extjs/static/resources/license.txt
tw/extjs/static/resources/resources.jsb
tw/extjs/static/resources/css/Multiselect.css
