Metadata-Version: 1.0
Name: tw.extjs
Version: 0.9.0
Summary: ToscaWidgets wrapper around ExtJS 1.0.2 (http://extjs.com) javascript library
Home-page: http://toscawidgets.org
Author: Alberto Valverde, Christopher Perkins, Sanjiv Singh
Author-email: alberto@toscat.net
License: UNKNOWN
Download-URL: http://toscawidgets.org/download
Keywords: toscawidgets.widgets
Platform: UNKNOWN
